routine_workflow/__init__.py
routine_workflow/backup_service.py
routine_workflow/banner.py
routine_workflow/cli.py
routine_workflow/config.py
routine_workflow/config_loader.py
routine_workflow/constants.py
routine_workflow/defaults.py
routine_workflow/errors.py
routine_workflow/formatting_service.py
routine_workflow/help_renderer.py
routine_workflow/lock.py
routine_workflow/pre_commit_installer.py
routine_workflow/prompt_service.py
routine_workflow/runner.py
routine_workflow/utils.py
routine_workflow/steps/__init__.py
routine_workflow/steps/step1.py
routine_workflow/steps/step2.py
routine_workflow/steps/step2_5.py
routine_workflow/steps/step3.py
routine_workflow/steps/step3_5.py
routine_workflow/steps/step4.py
routine_workflow/steps/step5.py
routine_workflow/steps/step6.py
routine_workflow/steps/step6_5.py
routine_workflow-10.0.1.dist-info/METADATA
routine_workflow-10.0.1.dist-info/WHEEL
routine_workflow-10.0.1.dist-info/entry_points.txt
routine_workflow-10.0.1.dist-info/RECORD
