Metadata-Version: 2.4
Name: routine-workflow
Version: 10.0.1
Summary: Automated routine workflow runner for repository hygiene, backups, and dumps orchestration and much more.
Project-URL: Homepage, https://github.com/dhruv13x/routine-workflow
Project-URL: Repository, https://github.com/dhruv13x/routine-workflow
Project-URL: Issues, https://github.com/dhruv13x/routine-workflow/issues
Project-URL: Documentation, https://pypi.org/project/routine-workflow
Author-email: dhruv13x <dhruv13x@gmail.com>
License: MIT
Requires-Python: >=3.9
Requires-Dist: argparse; python_version < '3.10'
Requires-Dist: coverage[toml]>=7.5.0
Requires-Dist: create-dump
Requires-Dist: projectclone
Requires-Dist: pypurge
Requires-Dist: pytest>=8.0.0
Requires-Dist: tomli; python_version < '3.11'
Requires-Dist: typing-extensions>=4.0
Provides-Extra: dev
Requires-Dist: black>=24.3.0; extra == 'dev'
Requires-Dist: mypy>=1.11.0; extra == 'dev'
Requires-Dist: pyfakefs>=5.0.0; extra == 'dev'
Requires-Dist: pytest-asyncio>=0.23.0; extra == 'dev'
Requires-Dist: pytest-cov>=5.0.0; extra == 'dev'
Requires-Dist: pytest-json-report>=1.5.0; extra == 'dev'
Requires-Dist: pytest-mock>=3.10.0; extra == 'dev'
Requires-Dist: pytest-timeout>=2.2.0; extra == 'dev'
Requires-Dist: pytest>=8.0.0; extra == 'dev'
Requires-Dist: pyyaml>=6.0; extra == 'dev'
Requires-Dist: ruff>=0.6.0; extra == 'dev'
Requires-Dist: types-pyyaml>=6.0; extra == 'dev'
